JPYForex/__init__.py
JPYForex/jpyforex.py
jpyforex-0.1.dist-info/LICENSE
jpyforex-0.1.dist-info/METADATA
jpyforex-0.1.dist-info/WHEEL
jpyforex-0.1.dist-info/top_level.txt
jpyforex-0.1.dist-info/RECORD
