Metadata-Version: 2.1
Name: jpyforex
Version: 0.1
Summary: jpyforex: Retrieve the exchange rate quoted in Japanese Yen (JPY).
Author-email: HideyukiO <hogawa098@gmail.com>
License: MIT License
Project-URL: Repository, https://github.com/mazarimono/JPYForex
Keywords: Japanese Yen
Classifier: Programming Language :: Python :: 3
Classifier: Programming Language :: Python :: 3.10
Classifier: Programming Language :: Python :: 3.11
Requires-Python: >=3.10
License-File: LICENSE
Requires-Dist: pandas-datareader
Provides-Extra: dev
Requires-Dist: black ; extra == 'dev'
Requires-Dist: isort ; extra == 'dev'
Requires-Dist: flake8 ; extra == 'dev'
Requires-Dist: mypy ; extra == 'dev'
Requires-Dist: pytest ; extra == 'dev'
